sg1/__init__.py
sg1/commands.py
sg1/manage.py
sg1/render.py
sg1/settings.py
sg1/helpers/__init__.py
sg1/helpers/directory.py
sg1-0.1.4.dist-info/LICENSE.txt
sg1-0.1.4.dist-info/METADATA
sg1-0.1.4.dist-info/WHEEL
sg1-0.1.4.dist-info/entry_points.txt
sg1-0.1.4.dist-info/top_level.txt
sg1-0.1.4.dist-info/RECORD
