Metadata-Version: 2.1
Name: sg1
Version: 0.1.4
Summary: A stupid, simple, static site generator
Home-page: https://github.com/mjlabe/sg1
Author: Marc LaBelle
License: MIT
Keywords: SIMPLE,STATIC,SITE,GENERATOR
Platform: UNKNOWN
Classifier: Development Status :: 3 - Alpha
Classifier: License :: OSI Approved :: MIT License
Classifier: Programming Language :: Python :: 3.7
Requires-Python: >=3.6, <4
Requires-Dist: Jinja2 (>=2.11.3)
Requires-Dist: MarkupSafe (>=1.1.1)
